{
  "particles": {
    "number": {
      "value": 20
    },
      "color": {
          "value":"#ffffff"
      }, 
      "size": {
          "value":5
      },
      "opacity": {
          "value": 0.7
      }, 
      "line_linked": {
          "color" : "#ffffff",
          "opacity" : 0.35,
          "distance": 200
      }
  },
    "interactivity": {
          "events": {
              "onhover": {
                  "enable":false, 
                  "mode": "bubbles"
              },
              "onclick": {
                  "enable": false,
                  "mode": "repulse"
              },
              "modes": {
                  "bubbles": {
                      "distance": 20,
                      "size": 5
                  }
              }
          }
      }
}